openbb_multpl/__init__.py
openbb_multpl/models/__init__.py
openbb_multpl/models/sp500_multiples.py
openbb_multpl/utils/__init__.py
openbb_multpl-1.2.1.dist-info/METADATA
openbb_multpl-1.2.1.dist-info/WHEEL
openbb_multpl-1.2.1.dist-info/entry_points.txt
openbb_multpl-1.2.1.dist-info/RECORD
